crypto_plus/__init__.py
crypto_plus/asymmetric.py
crypto_plus/base.py
crypto_plus/compatible.py
crypto_plus/encrypt.py
crypto_plus/key.py
crypto_plus/sign.py
crypto_plus-1.0.6.dist-info/entry_points.txt
crypto_plus-1.0.6.dist-info/LICENSE
crypto_plus-1.0.6.dist-info/METADATA
crypto_plus-1.0.6.dist-info/WHEEL
crypto_plus-1.0.6.dist-info/RECORD
